MANIFEST.in
README.md
pyproject.toml
requirements.txt
setup.cfg
setup.py
t_pom_dentalhub/__init__.py
t_pom_dentalhub/exceptions.py
t_pom_dentalhub/t_pom_dentalhub.py
t_pom_dentalhub.egg-info/PKG-INFO
t_pom_dentalhub.egg-info/SOURCES.txt
t_pom_dentalhub.egg-info/dependency_links.txt
t_pom_dentalhub.egg-info/not-zip-safe
t_pom_dentalhub.egg-info/requires.txt
t_pom_dentalhub.egg-info/top_level.txt
t_pom_dentalhub/elements/__init__.py
t_pom_dentalhub/elements/table_element.py
t_pom_dentalhub/elements/text_element.py
t_pom_dentalhub/pages/__init__.py
t_pom_dentalhub/pages/dashboard_page.py
t_pom_dentalhub/pages/eligibility_check_results_page.py
t_pom_dentalhub/pages/eligibility_selected_insurance_page.py
t_pom_dentalhub/pages/login_page.py
t_pom_dentalhub/pages/multi_factor_authentication_page.py
t_pom_dentalhub/pages/patient_insurance_page.py
t_pom_dentalhub/pages/practitioner_location_page.py
t_pom_dentalhub/pages/service_history_page.py
tests/test_t_pom_dentalhub.py